cinnamon_tf/__init__.py
cinnamon_tf/components/__init__.py
cinnamon_tf/components/callback.py
cinnamon_tf/components/helper.py
cinnamon_tf/components/model.py
cinnamon_tf/configurations/__init__.py
cinnamon_tf/configurations/callback.py
cinnamon_tf/configurations/helper.py
cinnamon_tf-0.1.dist-info/LICENSE
cinnamon_tf-0.1.dist-info/METADATA
cinnamon_tf-0.1.dist-info/WHEEL
cinnamon_tf-0.1.dist-info/top_level.txt
cinnamon_tf-0.1.dist-info/RECORD
