Metadata-Version: 2.1
Name: cinnamon-tf
Version: 0.1
Summary: [Tensorflow Package] A simple high-level framework for research
Home-page: https://github.com/federicoruggeri/cinnamon_tf
Author: Federico Ruggeri
Author-email: federico.ruggeri6@unibo.it
License: MIT
Project-URL: Bug Tracker, https://github.com/federicoruggeri/cinnamon_tf/issues
Platform: UNKNOWN
Classifier: Programming Language :: Python :: 3
Classifier: Operating System :: OS Independent
Requires-Python: >=3.6
